05/report/9931078-9931072/codes/decoder_2_4/decoder_2_4.v
module decoder_2_4(a,b,enb,O0,O1,O2,O3);
    input a,b,enb;
    output O0,O1,O2,O3;
    not g1(a_not, a);
    not g2(b_not, b);
    and g3(O0, a_not, b_not, enb);
    and g4(O1, a_not, b, enb);
    and g5(O2, a, b_not, enb);
    and g6(O3, a, b, enb);
endmodule

05/report/9931078-9931072/codes/decoder_2_4/decoder_2_4_tb.v
`include "./decoder_2_4.v"
`timescale 1ps/1ps

module decoder_tb;
reg a,b,enable;
wire o0, o1, o2, o3;
decoder_2_4 test_target(a,b,enable, o0, o1, o2, o3);

initial begin
    $dumpfile("decoder.vcd");
    $dumpvars(0, decoder_tb);

    // test for disabled sitatuion
    a =0; b =0; enable = 0;
    #100 a =0; b =1; enable = 0;
    #100 a =1; b =0; enable = 0;
    #100 a =1; b =1; enable = 0;

    // test for disbaled status
    #100 a =0; b =0; enable = 1;
    #100 a =0; b =1; enable = 1;
    #100 a =1; b =0; enable = 1;
    #100 a =1; b =1; enable = 1;
    #100 $finish;
end
endmodule

05/report/9931078-9931072/codes/decoder_2_4/decoder.vcd
$date
	Sun Nov  7 18:08:32 2021
$end
$version
	Icarus Verilog
$end
$timescale
	1ps
$end
$scope module decoder_tb $end
$var wire 1 ! o3 $end
$var wire 1 " o2 $end
$var wire 1 # o1 $end
$var wire 1 $ o0 $end
$var reg 1 % a $end
$var reg 1 & b $end
$var reg 1 ' enable $end
$scope module test_target $end
$var wire 1 $ O0 $end
$var wire 1 # O1 $end
$var wire 1 " O2 $end
$var wire 1 ! O3 $end
$var wire 1 % a $end
$var wire 1 ( a_not $end
$var wire 1 & b $end
$var wire 1 ) b_not $end
$var wire 1 ' enb $end
$upscope $end
$upscope $end
$enddefinitions $end
#0
$dumpvars
1)
1(
0'
0&
0%
0$
0#
0"
0!
$end
#100
0)
1&
#200
1)
0(
0&
1%
#300
0)
1&
#400
1$
1)
1(
1'
0&
0%
#500
0$
0)
1#
1&
#600
1"
1)
0#
0(
0&
1%
#700
0"
0)
1!
1&
