05/report/9931078-9931072/codes/encoder/encoder.v
module encoder (d0,d1,d2,d3, o0,o1);
input d0, d1, d2, d3;
output o0,o1;

assign o0  = d3 | (d1 & ~d2);
assign o1 = d2 | d3;

endmodule

05/report/9931078-9931072/codes/encoder/encoder_tb.v
`include "./encoder.v"
`timescale 1ps/1ps
module encoder_tb;
reg d0,d1,d2,d3;
wire o0,o1;

encoder test_target(d0,d1,d2,d3, o0,o1);

initial begin
    $dumpfile("encoder.vcd");
    $dumpvars(0, encoder_tb);

    d0 = 0; d1 = 0; d2 = 0; d3 = 0;
    #100 d0 = 0; d1 = 0; d2 = 0; d3 = 1;
    #100 d0 = 0; d1 = 0; d2 = 1; d3 = 0;
    #100 d0 = 0; d1 = 0; d2 = 1; d3 = 1;
    #100 d0 = 0; d1 = 1; d2 = 0; d3 = 0;
    #100 d0 = 0; d1 = 1; d2 = 0; d3 = 1;
    #100 d0 = 0; d1 = 1; d2 = 1; d3 = 0;
    #100 d0 = 0; d1 = 1; d2 = 1; d3 = 1;

    #100 d0 = 1; d1 = 0; d2 = 0; d3 = 0;
    #100 d0 = 1; d1 = 0; d2 = 0; d3 = 1;
    #100 d0 = 1; d1 = 0; d2 = 1; d3 = 0;
    #100 d0 = 1; d1 = 0; d2 = 1; d3 = 1;
    #100 d0 = 1; d1 = 1; d2 = 0; d3 = 0;
    #100 d0 = 1; d1 = 1; d2 = 0; d3 = 1;
    #100 d0 = 1; d1 = 1; d2 = 1; d3 = 0;
    #100 d0 = 1; d1 = 1; d2 = 1; d3 = 1;
    $finish;
end
endmodule

05/report/9931078-9931072/codes/encoder/encoder.vcd
$date
	Sun Nov  7 19:12:33 2021
$end
$version
	Icarus Verilog
$end
$timescale
	1ps
$end
$scope module encoder_tb $end
$var wire 1 ! o1 $end
$var wire 1 " o0 $end
$var reg 1 # d0 $end
$var reg 1 $ d1 $end
$var reg 1 % d2 $end
$var reg 1 & d3 $end
$scope module test_target $end
$var wire 1 # d0 $end
$var wire 1 $ d1 $end
$var wire 1 % d2 $end
$var wire 1 & d3 $end
$var wire 1 " o0 $end
$var wire 1 ! o1 $end
$upscope $end
$upscope $end
$enddefinitions $end
#0
$dumpvars
0&
0%
0$
0#
0"
0!
$end
#100
1"
1!
1&
#200
0"
0&
1%
#300
1"
1&
#400
1"
0!
0&
0%
1$
#500
1!
1&
#600
0"
0&
1%
#700
1"
1&
#800
0"
0!
0&
0%
0$
1#
#900
1"
1!
1&
#1000
0"
0&
1%
#1100
1"
1&
#1200
1"
0!
0&
0%
1$
#1300
1!
1&
#1400
0"
0&
1%
#1500
1"
1&
