05/report/9931078-9931072/codes/multiplexer/multiplexer.v
module multiplexer(s1, s0, i0, i1, i2, i3, result);
input s1, s0, i0, i1, i2, i3;
output result;

assign result = (~s0 & ~s1 & i0) | (~s1 & s0 & i1) | (s1 & ~s0 & i2) | (s1 & s0 & i0);
endmodule

05/report/9931078-9931072/codes/multiplexer/multiplexer_tb.v
`include "./multiplexer.v"
`timescale 1ps/1ps
module multiplexer_tb;
reg a,b, i0, i1, i2, i3;
wire result;

multiplexer test_target(a, b, i0, i1, i2, i3, result);

initial begin
    $dumpfile("multiplexer.vcd");
    $dumpvars(0, multiplexer_tb);

    a= 0; b = 0; i0 = 1; i1 = 0; i2 = 0; i3 = 0;
    #100 a= 0; b = 0; i0 = 0; i1 = 0; i2 = 0; i3 = 0;

    #100 a= 0; b = 1; i0 = 0; i1 = 1; i2 = 0; i3 = 0;
    #100 a= 0; b = 0; i0 = 0; i1 = 0; i2 = 0; i3 = 0;

    #100 a= 1; b = 0; i0 = 0; i1 = 0; i2 = 1; i3 = 0;
    #100 a= 1; b = 0; i0 = 0; i1 = 1; i2 = 0; i3 = 0;

    #100 a= 1; b = 1; i0 = 0; i1 = 0; i2 = 0; i3 = 1;
    #100 a= 1; b = 1; i0 = 0; i1 = 1; i2 = 0; i3 = 0;
    #100 $finish;
end
endmodule

05/report/9931078-9931072/codes/multiplexer/multiplexer.vcd
$date
	Sun Nov  7 19:17:13 2021
$end
$version
	Icarus Verilog
$end
$timescale
	1ps
$end
$scope module multiplexer_tb $end
$var wire 1 ! result $end
$var reg 1 " a $end
$var reg 1 # b $end
$var reg 1 $ i0 $end
$var reg 1 % i1 $end
$var reg 1 & i2 $end
$var reg 1 ' i3 $end
$scope module test_target $end
$var wire 1 $ i0 $end
$var wire 1 % i1 $end
$var wire 1 & i2 $end
$var wire 1 ' i3 $end
$var wire 1 ! result $end
$var wire 1 # s0 $end
$var wire 1 " s1 $end
$upscope $end
$upscope $end
$enddefinitions $end
#0
$dumpvars
0'
0&
0%
1$
0#
0"
1!
$end
#100
0!
0$
#200
1!
1%
1#
#300
0!
0%
0#
#400
1!
1&
1"
#500
0!
0&
1%
#600
1'
0%
1#
#700
0'
1%
